geopicker/__init__.py
geopicker/geopicker.py
geopicker-0.1.dist-info/DESCRIPTION.rst
geopicker-0.1.dist-info/METADATA
geopicker-0.1.dist-info/RECORD
geopicker-0.1.dist-info/WHEEL
geopicker-0.1.dist-info/metadata.json
geopicker-0.1.dist-info/top_level.txt
