Metadata-Version: 2.0
Name: geopicker
Version: 0.1
Summary: UNKNOWN
Home-page: UNKNOWN
Author: UNKNOWN
Author-email: UNKNOWN
License: Creative Commons Attribution-Noncommercial-Share Alike license
Platform: UNKNOWN
Requires-Dist: geopandas
Requires-Dist: pandas
Requires-Dist: shapely
